co2wui
