Metadata-Version: 2.1
Name: co2wui
Version: 0.0.13
Summary: WebUI for co2mpas
Home-page: https://github.com/JRCSTU/co2wui
License: European Union Public Licence 1.1 or later (EUPL 1.1+)
Project-URL: Documentation, https://co2mpas.io/
Project-URL: Sources, https://github.com/JRCSTU/co2wui
Keywords: automotive,vehicles,simulator,WLTP,web-app
Platform: UNKNOWN
Classifier: Programming Language :: Python
Classifier: Programming Language :: Python :: 3
Classifier: Programming Language :: Python :: 3.5
Classifier: Programming Language :: Python :: 3.6
Classifier: Programming Language :: Python :: 3.7
Classifier: Programming Language :: Python :: Implementation :: CPython
Classifier: Development Status :: 3 - Alpha
Classifier: Natural Language :: English
Classifier: Intended Audience :: Developers
Classifier: Intended Audience :: Science/Research
Classifier: Intended Audience :: Manufacturing
Classifier: Environment :: Console
Classifier: License :: OSI Approved :: European Union Public Licence 1.1 (EUPL 1.1)
Classifier: Natural Language :: English
Classifier: Operating System :: MacOS :: MacOS X
Classifier: Operating System :: Microsoft :: Windows
Classifier: Operating System :: POSIX
Classifier: Operating System :: Unix
Classifier: Operating System :: OS Independent
Classifier: Topic :: Scientific/Engineering
Classifier: Topic :: Scientific/Engineering :: Information Analysis
Requires-Python: >=3.6
Provides-Extra: dev
Provides-Extra: test
Provides-Extra: ta
